LICENSE.txt
README.md
pyproject.toml
setup.py
src/pwinput/__init__.py
src/pwinput/__main__.py
src/pwinput.egg-info/PKG-INFO
src/pwinput.egg-info/SOURCES.txt
src/pwinput.egg-info/dependency_links.txt
src/pwinput.egg-info/top_level.txt